galileo_cli/__init__.py
galileo_cli/cli.py
galileo_cli/jobs.py
galileo_cli/machines.py
galileo_cli/profiles.py
galileo_cli/projects.py
galileo_cli/stations.py
galileo_cli-0.0.15.dist-info/METADATA
galileo_cli-0.0.15.dist-info/WHEEL
galileo_cli-0.0.15.dist-info/entry_points.txt
galileo_cli-0.0.15.dist-info/top_level.txt
galileo_cli-0.0.15.dist-info/RECORD
