Metadata-Version: 2.1
Name: galileo-cli
Version: 0.0.15
Summary: UNKNOWN
Home-page: UNKNOWN
Author: Hypernet Labs
License: MIT
Platform: UNKNOWN
Requires-Python: >=3.6.7
Requires-Dist: requests (>=2.21.0)
Requires-Dist: python-socketio
Requires-Dist: termcolor (==1.1.0)
Requires-Dist: colorama (==0.4.3)
Requires-Dist: pyfiglet
Requires-Dist: click
Requires-Dist: click-shell
Requires-Dist: pandas (==1.0.1)
Requires-Dist: galileo-sdk (>=0.0.23)
Requires-Dist: halo
Provides-Extra: docs
Requires-Dist: sphinx (>=2.2.0) ; extra == 'docs'
Requires-Dist: sphinx-material ; extra == 'docs'
